zope.app.content-5.0-py3.9-nspkg.pth
zope/app/content/__init__.py
zope/app/content/configure.zcml
zope/app/content/interfaces.py
zope/app/content/tests.py
zope.app.content-5.0.dist-info/LICENSE.txt
zope.app.content-5.0.dist-info/METADATA
zope.app.content-5.0.dist-info/WHEEL
zope.app.content-5.0.dist-info/namespace_packages.txt
zope.app.content-5.0.dist-info/top_level.txt
zope.app.content-5.0.dist-info/RECORD
